agent_memory_hub/__init__.py
agent_memory_hub/client/__init__.py
agent_memory_hub/client/memory_client.py
agent_memory_hub/config/__init__.py
agent_memory_hub/config/alloydb_config.py
agent_memory_hub/config/redis_config.py
agent_memory_hub/config/regions.py
agent_memory_hub/control_plane/__init__.py
agent_memory_hub/control_plane/region_contract.py
agent_memory_hub/control_plane/region_guard.py
agent_memory_hub/data_plane/__init__.py
agent_memory_hub/data_plane/adk_session_store.py
agent_memory_hub/data_plane/alloydb_session_store.py
agent_memory_hub/data_plane/firestore_session_store.py
agent_memory_hub/data_plane/redis_session_store.py
agent_memory_hub/data_plane/store_factory.py
agent_memory_hub/models/__init__.py
agent_memory_hub/models/base.py
agent_memory_hub/models/types.py
agent_memory_hub/routing/__init__.py
agent_memory_hub/routing/memory_router.py
agent_memory_hub/utils/__init__.py
agent_memory_hub/utils/telemetry.py
agent_memory_hub/utils/ttl_manager.py
agent_memory_hub-0.3.6.dist-info/licenses/LICENSE
agent_memory_hub-0.3.6.dist-info/METADATA
agent_memory_hub-0.3.6.dist-info/WHEEL
agent_memory_hub-0.3.6.dist-info/top_level.txt
agent_memory_hub-0.3.6.dist-info/RECORD
