Metadata-Version: 2.4
Name: agent-memory-hub
Version: 0.3.6
Summary: Enterprise-grade agent memory management solution with region governance.
Author-email: Agent Memory Hub Maintainers <maintainers@example.com>
License:                                  Apache License
Project-URL: Homepage, https://github.com/example/agent-memory-hub
Project-URL: Bug Tracker, https://github.com/example/agent-memory-hub/issues
Classifier: Development Status :: 4 - Beta
Classifier: Intended Audience :: Developers
Classifier: License :: OSI Approved :: Apache Software License
Classifier: Programming Language :: Python :: 3
Classifier: Programming Language :: Python :: 3.10
Classifier: Programming Language :: Python :: 3.11
Classifier: Programming Language :: Python :: 3.12
Classifier: Operating System :: POSIX :: Linux
Classifier: Operating System :: MacOS
Classifier: Topic :: Software Development :: Libraries :: Python Modules
Requires-Python: >=3.9
License-File: LICENSE
Requires-Dist: pydantic>=2.0.0
Requires-Dist: google-cloud-storage>=2.0.0
Requires-Dist: tenacity>=8.0.0
Requires-Dist: opentelemetry-api>=1.20.0
Provides-Extra: dev
Requires-Dist: pytest>=7.0.0; extra == "dev"
Requires-Dist: pytest-cov>=4.0.0; extra == "dev"
Requires-Dist: ruff>=0.1.0; extra == "dev"
Requires-Dist: pip-audit>=2.0.0; extra == "dev"
Requires-Dist: mkdocs>=1.5.0; extra == "dev"
Requires-Dist: mkdocs-material>=9.5.0; extra == "dev"
Requires-Dist: mkdocstrings[python]>=0.24.0; extra == "dev"
Requires-Dist: bandit>=1.7.0; extra == "dev"
Requires-Dist: opentelemetry-sdk>=1.20.0; extra == "dev"
Provides-Extra: alloydb
Requires-Dist: google-cloud-alloydb-connector[pg8000]>=1.0.0; extra == "alloydb"
Requires-Dist: sqlalchemy>=2.0.0; extra == "alloydb"
Requires-Dist: pg8000>=1.30.0; extra == "alloydb"
Provides-Extra: redis
Requires-Dist: redis>=5.0.0; extra == "redis"
Provides-Extra: firestore
Requires-Dist: google-cloud-firestore>=2.0.0; extra == "firestore"
Dynamic: license-file
